prefixed_id_beanie/__init__.py
prefixed_id_beanie/types/__init__.py
prefixed_id_beanie/types/prefixed_id.py
prefixed_id_beanie-0.3.2.dist-info/METADATA
prefixed_id_beanie-0.3.2.dist-info/WHEEL
prefixed_id_beanie-0.3.2.dist-info/top_level.txt
prefixed_id_beanie-0.3.2.dist-info/RECORD
