Metadata-Version: 2.1
Name: prefixed_id_beanie
Version: 0.3.2
Summary: A utility library for prefixed IDs using Beanie
Home-page: https://github.com/DanielDls-exe/prefixed_id_beanie
Author: Daniel Alvarado
Author-email: danieldls.ucv@gmail.com
Classifier: Development Status :: 4 - Beta
Classifier: Programming Language :: Python :: 3
Classifier: License :: OSI Approved :: MIT License
Classifier: Operating System :: OS Independent
Requires-Python: >=3.6
Requires-Dist: beanie
